{
"model_type": "Deep_NN",
"agent_name": "CACLA",
"data_folder": "Good_Anchors/",
"epsilon": 0.001, 
"omega": 0.002,
"batch_size": 32,
"learning_rate": 0.005,
"anchor_file": "../data/anchorData/easy_anchors_generated_from_controller.json",
"sim_config_file": "../data/pendulumContinuousActions/trainContinuousActions.ini",
"forwardDynamics_config_file": "../data/pendulumContinuousActions/trainContinuousActions.ini",
"num_actions": 9,
"exploration_rate": 0.08,
"rounds": 500,
"epochs": 2,
"eval_epochs": 2,
"num_states": 5,
"discount_factor": 0.8,
"visualize_learning": true,
"save_trainData": true,
"train_forward_dynamics": false,
"visulaize_forward_dynamics": false,
"reward_bounds": [[-10.1],[0.0]],
"expereince_length": 2000,
"state_bounds": [[-0.14, 1.0,-8.05, -1.0, -1.0, -8.5, -5.0, -5.5, -5.0, -2.5, -5.0],
                 [ 2.14, 8.5, 5.00, 1.0, 1.0, 10.0, 5.0, 15.0,  5.0, 20.0, 5.0]],
"action_bounds": [[0.05,-0.75,0.05],
                  [0.2,-0.35,0.2]],
"discrete_actions": [[0.12,-0.64,0.15],
                [0.102,-0.4,0.15],
                [0.06,-0.64,0.115],
                [0.14,-0.65,0.05],
                [0.07,-0.65,0.15],
                [0.08,-0.65,0.1],
                [0.1,-0.70,0.175],
                [0.09,-0.6,0.15],
                [0.13,-0.62,0.125]], 		  
"action_space_continuous":true,
"train_on_validation_set":true,
"environment_type": "pendulum_env",
"forward_dynamics_predictor": "simulator_parallel",
"sampling_method": "SequentialMC",
"use_actor_policy_action_suggestion": true,
"num_uniform_action_samples": 3,
"look_ahead_planning_steps": 2,
"plotting_update_freq_num_rounds": 1,
"saving_update_freq_num_rounds": 10,
"num_available_threads": 1,
"queue_size_limit": 1,
"sim_action_per_training_update": 4,
"adaptive_samples": 10,
"num_adaptive_samples_to_keep": 50,
"use_actor_policy_action_variance_suggestion": false,
"exploration_method": "uniform_random",
"dropout_p": 0.1,
"regularization_weight": 0.0001,
"rho": 0.95,
"rms_epsilon": 0.000001,
"steps_until_target_network_update": 1000,
"epsilon_annealing": 0.2,
"state_normalization": "variance",
    "comment__": "load a pretrained model for the controller",
"load_saved_model": false,
	"comment__": "Number of updates the critic should perform per actor update",
"critic_updates_per_actor_update": 10,
"clamp_actions_to_stay_inside_bounds": false,
"bootstrap_samples": 100,
"bootsrap_with_discrete_policy": true,
"max_epoch_length": 100,
"reward_lower_bound": 0.0001,
"actions_per_update": 1,
"use_guided_policy_search" : true,
"training_updates_per_sim_action": 2,
"use_sampling_exploration": true,
"use_model_based_action_optimization": true,
"penalize_actions_outside_bounds": false,
"use_transfer_task_network": false,
"forward_dynamics_model_type": "model.ForwardDynamicsDenseNetworkDropout.ForwardDynamicsDenseNetworkDropout",
"save_experience_memory": false,
"train_rl_learning": true,
"use_back_on_track_forcing": false,
"visualize_forward_dynamics": false,
"fd_learning_rate": 0.01
}